taglib/__init__.py
taglib/taglib.py
tag_library-0.1.dist-info/METADATA
tag_library-0.1.dist-info/WHEEL
tag_library-0.1.dist-info/top_level.txt
tag_library-0.1.dist-info/RECORD
