Metadata-Version: 2.1
Name: tag_library
Version: 0.1
Summary: A library to append viral tags to posts automatically
